entity_resolver/__init__.py
entity_resolver/main.py
entity_resolver/scripts.py
entity_resolver/core/__init__.py
entity_resolver/core/evaluator.py
entity_resolver/core/graph.py
entity_resolver/core/resolver.py
entity_resolver/core/utils.py
entity_resolver/parser/__init__.py
entity_resolver/parser/graph_parser.py
entity_resolver/parser/ground_truth_parser.py
entity_resolver-0.3.1.dist-info/LICENSE
entity_resolver-0.3.1.dist-info/METADATA
entity_resolver-0.3.1.dist-info/WHEEL
entity_resolver-0.3.1.dist-info/entry_points.txt
entity_resolver-0.3.1.dist-info/top_level.txt
entity_resolver-0.3.1.dist-info/RECORD
