Metadata-Version: 2.1
Name: entity-resolver
Version: 0.3.1
Summary: A python package for collective entity resolution
Home-page: https://github.com/Terry1004/EntityResolution_Capstone
Author: Yijie Cao, Kai Kang, Xinxin Huang, Yiming Huang, Yiran Wang
Author-email: hym961004@gmail.com
License: MIT
Platform: UNKNOWN
Requires-Python: >=3.6.5
Requires-Dist: pandas (>=0.25.1)
Requires-Dist: numpy (>=1.17.2)
Requires-Dist: scikit-learn (>=0.21.3)
Requires-Dist: py-stringmatching (>=0.4.1)
Requires-Dist: matplotlib (>=3.1.2)
